sdxl.py
sdxl-1.0.0.dist-info/LICENSE
sdxl-1.0.0.dist-info/METADATA
sdxl-1.0.0.dist-info/WHEEL
sdxl-1.0.0.dist-info/top_level.txt
sdxl-1.0.0.dist-info/RECORD
