Metadata-Version: 2.1
Name: sdxl
Version: 1.0.0
Summary: Reverse engineered API of Stable Diffusion XL 1.0 ( Midjourney Alternative ), A text-to-image generative AI model that creates beautiful 1024x1024 images.
Home-page: https://github.com/KoushikNavuluri/stable-diffusion-xl-api/
Author: Koushik
Author-email: koushikk@outlook.com
License: MIT
Keywords: stable diffusion,ai,midjourney,API,requests,images,llm,sdxl,replicate
Classifier: Development Status :: 5 - Production/Stable
Classifier: Intended Audience :: Developers
Classifier: License :: OSI Approved :: MIT License
Classifier: Programming Language :: Python :: 3.7
Classifier: Programming Language :: Python :: 3
Classifier: Operating System :: Unix
Classifier: Operating System :: MacOS :: MacOS X
Classifier: Operating System :: Microsoft :: Windows
Requires-Python: >=3.7
License-File: LICENSE
Requires-Dist: requests
